phone_parser/__init__.py
phone_parser/country.py
phone_parser/phone.py
phone_parser/py.typed
phone_toolkit-0.1.0.dist-info/METADATA
phone_toolkit-0.1.0.dist-info/WHEEL
phone_toolkit-0.1.0.dist-info/licenses/LICENSE
phone_toolkit-0.1.0.dist-info/RECORD
