Metadata-Version: 2.4
Name: phone-toolkit
Version: 0.1.0
Summary: International phone number parsing, validation, and formatting library
Project-URL: Homepage, https://github.com/yourusername/phone-toolkit
Project-URL: Repository, https://github.com/yourusername/phone-toolkit
Project-URL: Issues, https://github.com/yourusername/phone-toolkit/issues
Author-email: alshin <alshin@126.com>
License: MIT
License-File: LICENSE
Keywords: formatting,international,parser,phone,validation
Classifier: Development Status :: 4 - Beta
Classifier: Intended Audience :: Developers
Classifier: License :: OSI Approved :: MIT License
Classifier: Programming Language :: Python :: 3
Classifier: Programming Language :: Python :: 3.10
Classifier: Programming Language :: Python :: 3.11
Classifier: Programming Language :: Python :: 3.12
Classifier: Programming Language :: Python :: 3.13
Classifier: Topic :: Communications :: Telephony
Classifier: Topic :: Software Development :: Libraries :: Python Modules
Classifier: Typing :: Typed
Requires-Python: >=3.10
Requires-Dist: pyyaml>=6.0
Provides-Extra: dev
Requires-Dist: mypy>=1.8.0; extra == 'dev'
Requires-Dist: pytest-cov>=4.1.0; extra == 'dev'
Requires-Dist: pytest>=8.0.0; extra == 'dev'
Requires-Dist: ruff>=0.2.0; extra == 'dev'
Requires-Dist: types-pyyaml>=6.0; extra == 'dev'
